GeoPrivacy/__init__.py
GeoPrivacy/mechanism.py
GeoPrivacy/metrics.py
GeoPrivacy/processor.py
GeoPrivacy-0.0.4.dist-info/LICENSE
GeoPrivacy-0.0.4.dist-info/METADATA
GeoPrivacy-0.0.4.dist-info/WHEEL
GeoPrivacy-0.0.4.dist-info/top_level.txt
GeoPrivacy-0.0.4.dist-info/RECORD
