Metadata-Version: 2.1
Name: GeoPrivacy
Version: 0.0.4
Summary: A python package for implementing geo-indistinguishability privacy mechanisms
Home-page: https://github.com/quao627/GeoPrivacy
Author: Ao Qu
Author-email: ao.qu@vanderbilt.edu
License: MIT
Platform: UNKNOWN
Classifier: Programming Language :: Python :: 3
Classifier: License :: OSI Approved :: MIT License
Classifier: Operating System :: OS Independent
License-File: LICENSE
Requires-Dist: geopy
Requires-Dist: numpy
Requires-Dist: networkx
Requires-Dist: gurobipy
Requires-Dist: scipy
